[
  {
    "day": {
      "id" : 1,
      "dates": [
        1478199600,
        1478804400,
        1479409200
      ]
    }
  },
  {
    "day": {
      "id": 2,
      "dates": [
        1480014000,
        1480618800
      ]
    }
  },
  {
    "day": {
      "id": 3,
      "dates": [
        1481223600,
        1481828400,
        1482433200
      ]
    }
  },
  {
    "day": {
      "id": 4,
      "dates": [
        1483038000,
        1483642800,
        1484247600
      ]
    }
  },
  {
    "day": {
      "id": 5,
      "dates": [
        1484852400,
        1485457200
      ]
    }
  },
  {
    "day": {
      "id": 6,
      "dates": [
        1486062000,
        1486666800,
        1487271600
      ]
    }
  },
  {
    "day": {
      "id": 7,
      "dates": [
        1487876400,
        1488481200,
        1489086000
      ]
    }
  },
  {
    "day": {
      "id": 8,
      "dates": [
        1489690800,
        1490295600
      ]
    }
  },
  {
    "day": {
      "id": 9,
      "dates": [
        1490896800,
        1491501600,
        1492106400
      ]
    }
  },
  {
    "day": {
      "id": 10,
      "dates": [
        1492711200,
        1493316000,
        1493920800
      ]
    }
  }
]
